BushangbanYeyouqian/README.md
BushangbanYeyouqian/__init__.py
BushangbanYeyouqian/__main__.py
BushangbanYeyouqian/file.epub
BushangbanYeyouqian/index.html
BushangbanYeyouqian/css/__init__.py
BushangbanYeyouqian/css/annotations.css
BushangbanYeyouqian/css/main.css
BushangbanYeyouqian/css/normalize.css
BushangbanYeyouqian/css/popup.css
BushangbanYeyouqian/font/__init__.py
BushangbanYeyouqian/font/fontello.eot
BushangbanYeyouqian/font/fontello.svg
BushangbanYeyouqian/font/fontello.ttf
BushangbanYeyouqian/font/fontello.woff
BushangbanYeyouqian/img/__init__.py
BushangbanYeyouqian/img/annotator-glyph-sprite.png
BushangbanYeyouqian/img/annotator-icon-sprite.png
BushangbanYeyouqian/img/apple-touch-icon.png
BushangbanYeyouqian/img/cancelfullscreen.png
BushangbanYeyouqian/img/close.png
BushangbanYeyouqian/img/fullscreen.png
BushangbanYeyouqian/img/loader.gif
BushangbanYeyouqian/img/menu-icon.png
BushangbanYeyouqian/img/save.png
BushangbanYeyouqian/img/saved.png
BushangbanYeyouqian/img/settings-s.png
BushangbanYeyouqian/img/settings.png
BushangbanYeyouqian/img/star.png
BushangbanYeyouqian/js/__init__.py
BushangbanYeyouqian/js/epub.js
BushangbanYeyouqian/js/epub.min.js
BushangbanYeyouqian/js/epub.min.map
BushangbanYeyouqian/js/hooks.min.js
BushangbanYeyouqian/js/hooks.min.map
BushangbanYeyouqian/js/reader.js
BushangbanYeyouqian/js/reader.js.map
BushangbanYeyouqian/js/reader.min.js
BushangbanYeyouqian/js/reader.min.map
BushangbanYeyouqian/js/hooks/__init__.py
BushangbanYeyouqian/js/hooks/extensions/__init__.py
BushangbanYeyouqian/js/hooks/extensions/highlight.js
BushangbanYeyouqian/js/libs/__init__.py
BushangbanYeyouqian/js/libs/jquery.min.js
BushangbanYeyouqian/js/libs/localforage.min.js
BushangbanYeyouqian/js/libs/screenfull.js
BushangbanYeyouqian/js/libs/screenfull.min.js
BushangbanYeyouqian/js/libs/zip.min.js
BushangbanYeyouqian/js/plugins/__init__.py
BushangbanYeyouqian/js/plugins/hypothesis.js
BushangbanYeyouqian/js/plugins/search.js
bushangban_yeyouqian-2022.10.15.0.dist-info/METADATA
bushangban_yeyouqian-2022.10.15.0.dist-info/WHEEL
bushangban_yeyouqian-2022.10.15.0.dist-info/entry_points.txt
bushangban_yeyouqian-2022.10.15.0.dist-info/top_level.txt
bushangban_yeyouqian-2022.10.15.0.dist-info/RECORD
